docs_versions_menu/__init__.py
docs_versions_menu/cli.py
docs_versions_menu/ext.py
docs_versions_menu/folder_spec.py
docs_versions_menu/groups.py
docs_versions_menu/parse_version.py
docs_versions_menu/version_data.py
docs_versions_menu/_css/badge_only.css
docs_versions_menu/_fonts/fontawesome-webfont.eot
docs_versions_menu/_fonts/fontawesome-webfont.svg
docs_versions_menu/_fonts/fontawesome-webfont.ttf
docs_versions_menu/_fonts/fontawesome-webfont.woff
docs_versions_menu/_fonts/fontawesome-webfont.woff2
docs_versions_menu/_script/versions.py
docs_versions_menu/_template/docs-versions-menu.js_t
docs_versions_menu/_template/index.html_t
docs_versions_menu-0.5.2.dist-info/LICENSE
docs_versions_menu-0.5.2.dist-info/METADATA
docs_versions_menu-0.5.2.dist-info/WHEEL
docs_versions_menu-0.5.2.dist-info/entry_points.txt
docs_versions_menu-0.5.2.dist-info/top_level.txt
docs_versions_menu-0.5.2.dist-info/RECORD
